pyhaversine.cp38-win_amd64.pyd
pyhaversine-0.0.4.dist-info/LICENSE
pyhaversine-0.0.4.dist-info/METADATA
pyhaversine-0.0.4.dist-info/WHEEL
pyhaversine-0.0.4.dist-info/top_level.txt
pyhaversine-0.0.4.dist-info/RECORD
