Metadata-Version: 2.1
Name: pyhaversine
Version: 0.0.4
Summary: Haversine function using pybind11
Home-page: https://github.com/luk-f/pyhaversine
Author: Lucas Foulon
Author-email: lucas.foulon@gmail.com
License: UNKNOWN
Platform: UNKNOWN
Requires-Python: >=3.6
Provides-Extra: test
Requires-Dist: pytest ; extra == 'test'
